<?xml version="1.0" encoding="utf-8"?>
<Monster xmlns:xsi="http://www.w3.org/2001/XMLSchema-instance" xmlns:xsd="http://www.w3.org/2001/XMLSchema">
  <Name>Nalfeshnee</Name>
  <Descriptions />
  <Source>Systems Reference Document v5.1</Source>
  <Size>Large</Size>
  <Keywords>
    <Keyword>
      <Name>fiend</Name>
    </Keyword>
    <Keyword>
      <Name>demon</Name>
    </Keyword>
  </Keywords>
  <Alignment>chaotic evil</Alignment>
  <AC>18</AC>
  <ACText>natural armor</ACText>
  <HP>184</HP>
  <HPRoll>16d10+96</HPRoll>
  <Speeds>
    <string>20 ft.</string>
    <string>fly 30 ft.</string>
  </Speeds>
  <Strength>21</Strength>
  <Dexterity>10</Dexterity>
  <Constitution>22</Constitution>
  <Intelligence>19</Intelligence>
  <Wisdom>12</Wisdom>
  <Charisma>15</Charisma>
  <Resistances>
    <string>cold</string>
    <string>fire</string>
    <string>lightning</string>
    <string>bludgeoning from nonmagical attacks</string>
    <string>piercing from nonmagical attacks</string>
    <string>slashing from nonmagical attacks</string>
  </Resistances>
  <Vulnerablities />
  <Immunities>
    <string>poison</string>
  </Immunities>
  <ConditionImmunities>
    <string>poisoned</string>
  </ConditionImmunities>
  <Senses>
    <string>truesight 120 ft.</string>
  </Senses>
  <PassivePerception>0</PassivePerception>
  <Languages>
    <string>Abyssal</string>
    <string>telepathy 120 ft.</string>
  </Languages>
  <CR>13</CR>
  <XP>10000</XP>
  <Traits>
    <MonsterTrait>
      <Name>Magic Resistance</Name>
      <Text>The nalfeshnee has advantage on saving throws against spells and other magical effects.</Text>
    </MonsterTrait>
  </Traits>
  <Actions>
    <MonsterTrait>
      <Name>Multiattack</Name>
      <Text>The nalfeshnee uses Horror Nimbus if it can. It then makes three attacks: one with its bite and two with its claws.</Text>
    </MonsterTrait>
    <MonsterAction>
      <Name>Bite</Name>
      <Text>Melee Weapon Attack: +10 to hit, reach 5 ft., one target. Hit: 32 (5d10 + 5) piercing damage.</Text>
      <AttackBonus>10</AttackBonus>
      <Damage>5d10+5</Damage>
    </MonsterAction>
    <MonsterAction>
      <Name>Claw</Name>
      <Text>Melee Weapon Attack: +10 to hit, reach 10 ft., one target. Hit: 15 (3d6 + 5) slashing damage.</Text>
      <AttackBonus>10</AttackBonus>
      <Damage>3d6+5</Damage>
    </MonsterAction>
    <MonsterTrait>
      <Name>Horror Nimbus (Recharge 5–6)</Name>
      <Text>The nalfeshnee magically emits scintillating, multicolored light. Each creature within 15 feet of the nalfeshnee that can see the light must succeed on a DC 15 Wisdom saving throw or be frightened for 1 minute. A creature can repeat the saving throw at the end of each of its turns, ending the effect on itself on a success. If a creature’s saving throw is successful or the effect ends for it, the creature is immune to the nalfeshnee’s Horror Nimbus for the next 24 hours.</Text>
    </MonsterTrait>
    <MonsterTrait>
      <Name>Teleport</Name>
      <Text>The nalfeshnee magically teleports, along with any equipment it is wearing or carrying, up to 120 feet to an unoccupied space it can see.</Text>
    </MonsterTrait>
  </Actions>
  <Reactions />
  <LegendaryActions />
  <SaveBonus />
  <SkillBonus />
  <Spells />
  <Slots />
</Monster>