<?xml version="1.0" encoding="utf-8"?>
<Spell xmlns:xsi="http://www.w3.org/2001/XMLSchema-instance" xmlns:xsd="http://www.w3.org/2001/XMLSchema">
  <Keywords>
    <Keyword>
      <Name>divination</Name>
    </Keyword>
    <Material>
      <Name>material</Name>
      <Components>pieces of eggshell from two different kinds of creatures</Components>
    </Material>
    <Keyword>
      <Name>ranged</Name>
    </Keyword>
    <Keyword>
      <Name>ritual</Name>
    </Keyword>
    <Keyword>
      <Name>somatic</Name>
    </Keyword>
    <Keyword>
      <Name>verbal</Name>
    </Keyword>
    <Keyword>
      <Name>wizard</Name>
    </Keyword>
  </Keywords>
  <CantripDamage />
  <Name>Telepathic Bond</Name>
  <CastingTime>1 action</CastingTime>
  <Range>30 feet</Range>
  <Duration>1 hour</Duration>
  <Level>5</Level>
  <Description>You forge a telepathic link among up to eight willing creatures of your choice within range, psychically linking each creature to all the others for the duration. Creatures with Intelligence scores of 2 or less aren’t affected by this spell.
Until the spell ends, the targets can communicate telepathically through the bond whether or not they have a common language. The communication is possible over any distance, though it can’t extend to other planes of existence.</Description>
  <Descriptions />
  <Source>Systems Reference Document v5.1</Source>
</Spell>